FeatureCloud/__init__.py
FeatureCloud/api/__init__.py
FeatureCloud/api/cli/__init__.py
FeatureCloud/api/cli/__main__.py
FeatureCloud/api/cli/app/__init__.py
FeatureCloud/api/cli/app/commands.py
FeatureCloud/api/cli/controller/__init__.py
FeatureCloud/api/cli/controller/commands.py
FeatureCloud/api/cli/test/__init__.py
FeatureCloud/api/cli/test/commands.py
FeatureCloud/api/cli/test/workflow/__init__.py
FeatureCloud/api/cli/test/workflow/commands.py
FeatureCloud/api/imp/__init__.py
FeatureCloud/api/imp/exceptions.py
FeatureCloud/api/imp/util.py
FeatureCloud/api/imp/app/__init__.py
FeatureCloud/api/imp/app/commands.py
FeatureCloud/api/imp/controller/__init__.py
FeatureCloud/api/imp/controller/commands.py
FeatureCloud/api/imp/test/__init__.py
FeatureCloud/api/imp/test/commands.py
FeatureCloud/api/imp/test/helper.py
FeatureCloud/api/imp/test/api/__init__.py
FeatureCloud/api/imp/test/api/controller.py
FeatureCloud/api/imp/test/api/backend/__init__.py
FeatureCloud/api/imp/test/api/backend/auth.py
FeatureCloud/api/imp/test/api/backend/project.py
FeatureCloud/app/__init__.py
FeatureCloud/app/api/__init__.py
FeatureCloud/app/api/http_ctrl.py
FeatureCloud/app/api/http_web.py
FeatureCloud/app/engine/__init__.py
FeatureCloud/app/engine/app.py
FeatureCloud/app/engine/library.py
FeatureCloud/workflow/__init__.py
FeatureCloud/workflow/app.py
FeatureCloud/workflow/controller.py
FeatureCloud/workflow/example_wf.py
FeatureCloud/workflow/workflow.py
FeatureCloud-0.1.0.dist-info/LICENSE
FeatureCloud-0.1.0.dist-info/METADATA
FeatureCloud-0.1.0.dist-info/WHEEL
FeatureCloud-0.1.0.dist-info/entry_points.txt
FeatureCloud-0.1.0.dist-info/top_level.txt
FeatureCloud-0.1.0.dist-info/RECORD
