Metadata-Version: 2.1
Name: FeatureCloud
Version: 0.1.0
Summary: Secure Federated Learning Platform
Home-page: https://github.com/FeatureCloud/app-template
Author: FeatureCloud
Author-email: mohammad.bakhtiari@uni-hamburg.de
Project-URL: Bug Tracker, https://github.com/FeatureCloud/app-template/issues
Classifier: Programming Language :: Python :: 3
Classifier: Operating System :: OS Independent
Requires-Python: >=3.7
License-File: LICENSE
Requires-Dist: bottle
Requires-Dist: jsonpickle
Requires-Dist: joblib
Requires-Dist: numpy
Requires-Dist: pydot
Requires-Dist: pyyaml
Requires-Dist: flake8 (~=3.9.2)
Requires-Dist: pycodestyle (~=2.7.0)
Requires-Dist: Click (~=8.0.1)
Requires-Dist: requests
Requires-Dist: urllib3 (~=1.26.6)
Requires-Dist: pandas (>=2.0)
Requires-Dist: pyinstaller
Requires-Dist: docker (==7.1.0)
Requires-Dist: gitpython
Requires-Dist: tqdm
